asyncio_time_travel/__init__.py
asyncio_time_travel/time_travel_util.py
asyncio_time_travel/version.py
asyncio_time_travel-0.3.0.dist-info/LICENSE
asyncio_time_travel-0.3.0.dist-info/METADATA
asyncio_time_travel-0.3.0.dist-info/WHEEL
asyncio_time_travel-0.3.0.dist-info/entry_points.txt
asyncio_time_travel-0.3.0.dist-info/top_level.txt
asyncio_time_travel-0.3.0.dist-info/RECORD
