Metadata-Version: 2.1
Name: asyncio-time-travel
Version: 0.3.0
Summary: Asyncio Time Travel Loop
Home-page: https://github.com/realcr/asyncio_time_travel
Author: real
Author-email: realcr@gmail.com
License: Apache 2.0
Keywords: asyncio testing time travel sleep
Classifier: Development Status :: 3 - Alpha
Classifier: Intended Audience :: Developers
Classifier: Topic :: Software Development :: Testing
Classifier: License :: OSI Approved :: Apache Software License
Classifier: Programming Language :: Python
Classifier: Programming Language :: Python :: 3 :: Only
Classifier: Programming Language :: Python :: 3.5
Classifier: Programming Language :: Python :: 3.6
Classifier: Programming Language :: Python :: 3.7
Classifier: Programming Language :: Python :: 3.8
Classifier: Programming Language :: Python :: 3.9
License-File: LICENSE
